pywe_jssdk/__init__.py
pywe_jssdk/jssdk.py
pywe_jssdk-1.1.0.dist-info/METADATA
pywe_jssdk-1.1.0.dist-info/RECORD
pywe_jssdk-1.1.0.dist-info/WHEEL
pywe_jssdk-1.1.0.dist-info/top_level.txt
